LICENSE
MANIFEST.in
README.md
requirements.txt
setup.py
discordSuperUtils/Ban.py
discordSuperUtils/Base.py
discordSuperUtils/Birthday.py
discordSuperUtils/CommandHinter.py
discordSuperUtils/Convertors.py
discordSuperUtils/Database.py
discordSuperUtils/Economy.py
discordSuperUtils/FiveM.py
discordSuperUtils/Imaging.py
discordSuperUtils/Infractions.py
discordSuperUtils/InviteTracker.py
discordSuperUtils/Kick.py
discordSuperUtils/Leveling.py
discordSuperUtils/Music.py
discordSuperUtils/Mute.py
discordSuperUtils/Paginator.py
discordSuperUtils/Prefix.py
discordSuperUtils/Punishments.py
discordSuperUtils/ReactionRoles.py
discordSuperUtils/Spotify.py
discordSuperUtils/__init__.py
discordSuperUtils/assets/1.png
discordSuperUtils/assets/2.png
discordSuperUtils/assets/3.png
discordSuperUtils/assets/dnd.png
discordSuperUtils/assets/font.ttf
discordSuperUtils/assets/gay.jpg
discordSuperUtils/assets/idle.png
discordSuperUtils/assets/offline.png
discordSuperUtils/assets/online.png
discordSuperUtils/assets/streaming.png
discordSuperUtils_splitted.egg-info/PKG-INFO
discordSuperUtils_splitted.egg-info/SOURCES.txt
discordSuperUtils_splitted.egg-info/dependency_links.txt
discordSuperUtils_splitted.egg-info/requires.txt
discordSuperUtils_splitted.egg-info/top_level.txt