Metadata-Version: 2.1
Name: discordSuperUtils-splitted
Version: 0.2.0
Summary: Discord Bot Development made easy!
Home-page: https://github.com/adam757521/discordSuperUtils-splitted/
Author: adam7100
License: MIT
Download-URL: https://github.com/adam757521/discordSuperUtils-splitted/archive/refs/tags/v0.1.9.tar.gz/
Keywords: discord,easy,discord.py,music,download,links,images,videos,audio,bot,paginator,economy,reaction,reaction roles,database,database manager
Platform: UNKNOWN
Classifier: Development Status :: 4 - Beta
Classifier: Intended Audience :: Developers
Classifier: Topic :: Software Development :: Build Tools
Classifier: License :: OSI Approved :: MIT License
Classifier: Programming Language :: Python :: 3
Classifier: Programming Language :: Python :: 3.4
Classifier: Programming Language :: Python :: 3.5
Classifier: Programming Language :: Python :: 3.6
